git_presets/__init__.py
git_presets/attr.py
git_presets/config.py
git_presets/context.py
git_presets/exceptions.py
git_presets/main.py
git_presets/cli/__init__.py
git_presets/cli/remove.py
git_presets/cli/set.py
git_presets/cli/show.py
git_presets/cli/unset.py
git_presets/cli/use.py
git_presets-0.1.0.dist-info/METADATA
git_presets-0.1.0.dist-info/WHEEL
git_presets-0.1.0.dist-info/entry_points.txt
git_presets-0.1.0.dist-info/licenses/LICENSE
git_presets-0.1.0.dist-info/RECORD
