Metadata-Version: 2.4
Name: git-presets
Version: 0.1.0
Summary: The CLI tool to use multiple git config presets easily.
Project-URL: Homepage, https://github.com/a4rcvv/git-presets
Project-URL: Documentation, https://github.com/a4rcvv/git-presets
Project-URL: Repository, https://github.com/a4rcvv/git-presets.git
Project-URL: Issues, https://github.com/a4rcvv/git-presets/issues
License-Expression: MIT
License-File: LICENSE
Classifier: Development Status :: 3 - Alpha
Classifier: Programming Language :: Python :: 3
Classifier: Programming Language :: Python :: 3.9
Classifier: Programming Language :: Python :: 3.10
Classifier: Programming Language :: Python :: 3.11
Classifier: Programming Language :: Python :: 3.12
Classifier: Programming Language :: Python :: 3.13
Requires-Python: >=3.9
Requires-Dist: pydantic>=2.10.6
Requires-Dist: typer>=0.15.2
